tk_garden/__init__.py
tk_garden/tk_garden.py
tk_garden-0.0.2.dist-info/LICENSE.txt
tk_garden-0.0.2.dist-info/METADATA
tk_garden-0.0.2.dist-info/RECORD
tk_garden-0.0.2.dist-info/WHEEL
tk_garden-0.0.2.dist-info/top_level.txt
