Metadata-Version: 2.1
Name: tk-garden
Version: 0.0.2
Summary: TK Garden Bot Controllers
Home-page: https://github.com/edtechkidsvn/tk-garden
Author: TechKids Coding School
Author-email: techkidsvn@gmail.com
License: UNKNOWN
Platform: UNKNOWN
Classifier: Programming Language :: Python :: 3
Classifier: License :: OSI Approved :: MIT License
Classifier: Operating System :: OS Independent
